lab4_spi/src/uart_tx.v
module uart_tx#(parameter transfer_speed = 4800, parameter package_size = 8, 
                parameter frequency = 27_000_000)
(
    input clk,
    input [package_size+1:0] data,
    input data_update_uart,
    output reg transmitted_signal = 1
);


    parameter count_of_strobe = frequency / transfer_speed;
    reg [26:0] count = 0;
    integer i = 0;
    reg [package_size + 1:0] recieved_data = 0;
    reg sending_data = 0;

    always @(posedge clk) begin
        if (data_update_uart || sending_data) begin
            if (i == package_size + 2) begin
                count = 0;
                i = 0;
                sending_data = 0;
            end
            else begin
                count = count + 1;
                if (count == 1) begin
                    sending_data = 1;
                    recieved_data = data;
                end
                transmitted_signal = recieved_data[i];
                if (count == count_of_strobe) begin
                    count = 0;
                    i = i + 1;
                end
            end
            
        end
        else begin
            transmitted_signal = 1;
        end
    end    
endmodule

lab4_spi/src/spi_slave.v
module spi_slave #(parameter package_size = 8)
(
    input clk_div,
    input MOSI,
    input SS,
    output reg MISO,
    output reg [package_size+1:0] data_output,
    output reg data_output_uart = 0
);

    integer i = 0;
    reg [26:0] count = 0;
    reg [package_size+1:0] data = 0;
    reg [package_size+1:0] data_to_send = 8'b10101010;

    //считывание с MOSI
    always @(negedge clk_div) begin
        if (!SS) begin
            count = count + 1;
            data = data >> 1;
            data[package_size+1] = MOSI;
            if (count == 10) begin
                data_output = data;
                count = 0;
                data_output_uart = 1;
            end
            else begin
                data_output_uart = 0;
            end
        end
    end

    //запись в  MISO
    always @(posedge clk_div) begin
        if (!SS) begin
            MISO = data_to_send[0];
            data_to_send[package_size-2:0] = data_to_send[package_size-1:1];
        end
        else begin
            data_to_send = 8'b10101010;
        end
    end
endmodule

lab4_spi/src/spi_master.v
module spi_master #(parameter package_size = 8)
(
    input clk_div,
    input [package_size+1:0] data,
    input data_update,
    input MISO,
    output reg MOSI,
    output reg SS = 1
);


    reg [package_size+1:0] recieved_data = 0;
    reg [package_size+1:0] temp_data;
    integer i = 0;
    
    
    //запись в MOSI
    always @(posedge clk_div) begin
        if (data_update) begin
            SS = 0;
            i = i + 1; 
            if (i == 1) begin
                temp_data = data;
            end
            if (i == package_size + 2) begin
                i <= 0;
            end
            MOSI = temp_data[0];
            temp_data = temp_data >> 1;
        end
        else begin
            SS = 1;
        end
    end

    //считывание с MISO
    always @(posedge clk_div) begin
        if (data_update) begin
            recieved_data = recieved_data >> 1;
            recieved_data[package_size-1] = MISO;
        end
    end
endmodule

lab4_spi/src/sending_data.v
module sending_data#(
    parameter transfer_speed = 4800,
    parameter package_size = 8, 
    parameter frequency = 27_000_000
)
(
    input clk,
    input button1,
    output reg [package_size+1:0] data,
    output reg data_update = 0,
    output clk_div
);

    integer i = 0;
    parameter debouncer_limit = (frequency / 100) + 1;
    parameter count_of_strobe = frequency / transfer_speed;
    reg [26:0] count = 0;
    reg [26:0] counter = 0;
    
    reg prev_button1 = 1;
    reg button1_pressed = 0;
    reg button1_stable = 0;
    reg [18:0] button1_counter = 0;
    reg [package_size-1:0] messages [0:26];

    assign data_ready = (button1_counter == debouncer_limit - 1) && (!button1);
    assign clk_div = (counter == 5400);

    initial begin
        messages[0] = 104;
        messages[1] = 101;
        messages[2] = 108;
        messages[3] = 108;
        messages[4] = 111;
        messages[5] = 44;
        messages[6] = 32;

        messages[7] = 118;
        messages[8] = 108;
        messages[9] = 97;
        messages[10] = 100;
        messages[11] = 105;
        messages[12] = 109;
        messages[13] = 105;
        messages[14] = 114;
        messages[15] = 32;

        messages[16] = 118;
        messages[17] = 105;
        messages[18] = 99;
        messages[19] = 116;
        messages[20] = 111;
        messages[21] = 114;
        messages[22] = 111;
        messages[23] = 118;
        messages[24] = 105;
        messages[25] = 99;
        messages[26] = 104;
    end

    always @(posedge clk) begin
        /*Начало устранение дребезга контактов на button1.*/
        if (!button1 && prev_button1) begin
            button1_pressed = 1;
        end
        else if (button1_pressed)
            button1_counter = button1_counter + 1;
        if (button1_counter == debouncer_limit)
            button1_stable = 1;
        /*Конец устранение дребезга контактов на button1.*/

        /*Кнопка button1 "явно" нажата.*/
        if (button1_stable && !button1) begin
            button1_stable = 0;
            button1_pressed = 0;
            button1_counter = 0;
        end
        prev_button1 = button1;
    end

    always @(posedge clk) begin
        if (counter == 5400) begin
            counter = 0;
        end
        else begin
            counter = counter + 1;
        end
    end

    always @(posedge clk_div) begin
        if (data_ready || data_update) begin
            data_update = 1;
            count = count + 1;
            if ((count == count_of_strobe * 10 + 2) && (i == 0)) begin
                i = i + 1;
                count = 1;
            end
            else if ((count == count_of_strobe * 10 + 1) && (i > 0)) begin
                i = i + 1;
                count = 1;
            end
            if (i == 27) begin
                count = 0;
                i = 0;
                data_update = 0;
            end
            else begin
                data = {1'b1, messages[i], 1'b0};
            end
        end
    end
endmodule

lab4_spi/src/top.v
module top (
    input clk,
    input button1,
    output MOSI,
    output MISO,
    output SS
);

    wire [9:0] data_input;
    wire [9:0] data_output;

    sending_data #(27_000_000, 8, 27_000_000) data_reader_inst (.clk(clk), .button1(button1), .data(data_input), .data_update(data_update), .clk_div(clk_div));
    spi_master #(8) spi_master_inst(.clk_div(clk_div), .data(data_input), .data_update(data_update), .MISO(MISO), .MOSI(MOSI), .SS(SS));
    spi_slave #(8) spi_slave_inst(.clk_div(clk_div), .MOSI(MOSI), .SS(SS), .MISO(MISO), .data_output(data_output), .data_output_uart(data_output_uart));
    uart_tx #(4800, 8, 27_000_000) uart_tx_inst(.clk(clk), .data(data_output), .data_update_uart(data_output_uart), .transmitted_signal(transmitted_signal));

endmodule

lab4_spi/src/testbench.v
`timescale 1 ms / 1 ms

module testbench();
    reg clk = 0;
    reg button1 = 1;
    wire MOSI, MISO, SS;
    top top_inst(
        .clk(clk),
        .button1(button1),
        .MOSI(MOSI),
        .MISO(MISO),
        .SS(SS)
    );

    always #5 clk = ~clk;
    initial begin
        $dumpvars;
        $display("Test started...");
        #100 button1 = ~button1;
        #100 button1 = ~button1;
        #10000 $finish;
    end

endmodule

lab4_spi/src/dump.vcd
$date
	Thu Dec 14 16:10:12 2023
$end
$version
	Icarus Verilog
$end
$timescale
	1ms
$end
$scope module testbench $end
$var wire 1 ! SS $end
$var wire 1 " MOSI $end
$var wire 1 # MISO $end
$var reg 1 $ button1 $end
$var reg 1 % clk $end
$scope module top_inst $end
$var wire 1 $ button1 $end
$var wire 1 % clk $end
$var wire 1 & transmitted_signal $end
$var wire 1 ' data_update $end
$var wire 1 ( data_output_uart $end
$var wire 10 ) data_output [9:0] $end
$var wire 10 * data_input [9:0] $end
$var wire 1 + clk_div $end
$var wire 1 ! SS $end
$var wire 1 " MOSI $end
$var wire 1 # MISO $end
$scope module data_reader_inst $end
$var wire 1 $ button1 $end
$var wire 1 % clk $end
$var wire 1 , data_ready $end
$var wire 1 + clk_div $end
$var reg 19 - button1_counter [18:0] $end
$var reg 1 . button1_pressed $end
$var reg 1 / button1_stable $end
$var reg 27 0 count [26:0] $end
$var reg 27 1 counter [26:0] $end
$var reg 10 2 data [9:0] $end
$var reg 1 ' data_update $end
$var reg 1 3 prev_button1 $end
$var integer 32 4 i [31:0] $end
$upscope $end
$scope module spi_master_inst $end
$var wire 1 + clk_div $end
$var wire 10 5 data [9:0] $end
$var wire 1 ' data_update $end
$var wire 1 # MISO $end
$var reg 1 " MOSI $end
$var reg 1 ! SS $end
$var reg 10 6 recieved_data [9:0] $end
$var reg 10 7 temp_data [9:0] $end
$var integer 32 8 i [31:0] $end
$upscope $end
$scope module spi_slave_inst $end
$var wire 1 " MOSI $end
$var wire 1 ! SS $end
$var wire 1 + clk_div $end
$var reg 1 # MISO $end
$var reg 27 9 count [26:0] $end
$var reg 10 : data [9:0] $end
$var reg 10 ; data_output [9:0] $end
$var reg 1 ( data_output_uart $end
$var reg 10 < data_to_send [9:0] $end
$var integer 32 = i [31:0] $end
$upscope $end
$scope module uart_tx_inst $end
$var wire 1 % clk $end
$var wire 10 > data [9:0] $end
$var wire 1 ( data_update_uart $end
$var reg 27 ? count [26:0] $end
$var reg 10 @ recieved_data [9:0] $end
$var reg 1 A sending_data $end
$var reg 1 & transmitted_signal $end
$var integer 32 B i [31:0] $end
$upscope $end
$upscope $end
$upscope $end
$enddefinitions $end
#0
$dumpvars
b0 B
0A
b0 @
b0 ?
bx >
b0 =
b10101010 <
bx ;
b0 :
b0 9
b0 8
bx 7
b0 6
bx 5
b0 4
13
bx 2
b0 1
b0 0
0/
0.
b0 -
0,
0+
bx *
bx )
0(
0'
1&
0%
1$
x#
x"
1!
$end
#5
1+
b1 1
1%
#10
0%
#15
0+
b0 1
1%
#20
0%
#25
1+
b1 1
1%
#30
0%
#35
0+
b0 1
1%
#40
0%
#45
1+
b1 1
1%
#50
0%
#55
0+
b0 1
1%
#60
0%
#65
1+
b1 1
1%
#70
0%
#75
0+
b0 1
1%
#80
0%
#85
1+
b1 1
1%
#90
0%
#95
0+
b0 1
1%
#100
0%
0$
#105
03
1.
1+
b1 1
1%
#110
0%
#115
1,
0+
b0 1
b1 -
1%
#120
0%
#125
0,
b1011010000 *
b1011010000 2
b1011010000 5
b1 0
1'
0.
0/
b0 -
1+
b1 1
1%
#130
0%
#135
0+
b0 1
1%
#140
0%
#145
b11010101 <
0#
b0x0000000 6
0"
b101101000 7
b1 8
0!
b10 0
1+
b1 1
1%
#150
0%
#155
b1 9
0+
b0 1
1%
#160
0%
#165
b11 0
b10110100 7
b10 8
b1x000000 6
b11101010 <
1#
1+
b1 1
1%
#170
0%
#175
b10 9
0+
b0 1
1%
#180
0%
#185
b11110101 <
0#
b11x00000 6
b1011010 7
b11 8
b100 0
1+
b1 1
1%
#190
0%
#195
b11 9
0+
b0 1
1%
#200
0%
1$
#205
b101 0
b101101 7
b100 8
b111x0000 6
b11111010 <
1#
13
1+
b1 1
1%
#210
0%
#215
b100 9
0+
b0 1
1%
#220
0%
#225
b11111101 <
0#
b1111x000 6
b10110 7
1"
b101 8
b110 0
1+
b1 1
1%
#230
0%
#235
b1000000000 :
b101 9
0+
b0 1
1%
#240
0%
#245
b111 0
b1011 7
0"
b110 8
b11111x00 6
b11111110 <
1#
1+
b1 1
1%
#250
0%
#255
b100000000 :
b110 9
0+
b0 1
1%
#260
0%
#265
b11111111 <
0#
b111111x0 6
b101 7
1"
b111 8
b1000 0
1+
b1 1
1%
#270
0%
#275
b1010000000 :
b111 9
0+
b0 1
1%
#280
0%
#285
b1001 0
b10 7
b1000 8
b1111111x 6
1#
1+
b1 1
1%
#290
0%
#295
b1101000000 :
b1000 9
0+
b0 1
1%
#300
0%
#305
b11111111 6
b1 7
0"
b1001 8
b1010 0
1+
b1 1
1%
#310
0%
#315
b110100000 :
b1001 9
0+
b0 1
1%
#320
0%
#325
b1011 0
b0 7
1"
b0 8
b11111111 6
1+
b1 1
1%
#330
0%
#335
1(
b1011010000 )
b1011010000 ;
b1011010000 >
b1011010000 :
b0 9
0+
b0 1
1%
#340
0%
#345
b11111111 6
0"
b101100101 7
b1 8
b1011001010 *
b1011001010 2
b1011001010 5
b1 4
b1 0
1+
b1 1
b1 B
0&
b1011010000 @
1A
b0 ?
1%
#350
0%
#355
0(
b101101000 :
b1 9
b10 B
b0 ?
0+
b0 1
1%
#360
0%
#365
b10 0
b10110010 7
1"
b10 8
b11111111 6
1+
b1 1
b11 B
b0 ?
1%
#370
0%
#375
b1010110100 :
b10 9
b100 B
b0 ?
0+
b0 1
1%
#380
0%
#385
b11111111 6
b1011001 7
0"
b11 8
b11 0
1+
b1 1
b101 B
1&
b0 ?
1%
#390
0%
#395
b101011010 :
b11 9
b110 B
0&
b0 ?
0+
b0 1
1%
#400
0%
#405
b100 0
b101100 7
1"
b100 8
b11111111 6
1+
b1 1
b111 B
1&
b0 ?
1%
#410
0%
#415
b1010101101 :
b100 9
b1000 B
b0 ?
0+
b0 1
1%
#420
0%
#425
b11111111 6
b10110 7
0"
b101 8
b101 0
1+
b1 1
b1001 B
0&
b0 ?
1%
#430
0%
#435
b101010110 :
b101 9
b1010 B
1&
b0 ?
0+
b0 1
1%
#440
0%
#445
b110 0
b1011 7
b110 8
b11111111 6
1+
b1 1
0A
b0 B
1%
#450
0%
#455
b10101011 :
b110 9
0+
b0 1
1%
#460
0%
#465
b11111111 6
b101 7
1"
b111 8
b111 0
1+
b1 1
1%
#470
0%
#475
b1001010101 :
b111 9
0+
b0 1
1%
#480
0%
#485
b1000 0
b10 7
b1000 8
b11111111 6
1+
b1 1
1%
#490
0%
#495
b1100101010 :
b1000 9
0+
b0 1
1%
#500
0%
#505
b11111111 6
b1 7
0"
b1001 8
b1001 0
1+
b1 1
1%
#510
0%
#515
b110010101 :
b1001 9
0+
b0 1
1%
#520
0%
#525
b1010 0
b0 7
1"
b0 8
b11111111 6
1+
b1 1
1%
#530
0%
#535
1(
b1011001010 )
b1011001010 ;
b1011001010 >
b1011001010 :
b0 9
0+
b0 1
1%
#540
0%
#545
b11111111 6
0"
b101101100 7
b1 8
b1011011000 *
b1011011000 2
b1011011000 5
b10 4
b1 0
1+
b1 1
b1 B
0&
b1011001010 @
1A
b0 ?
1%
#550
0%
#555
0(
b101100101 :
b1 9
b10 B
1&
b0 ?
0+
b0 1
1%
#560
0%
#565
b10 0
b10110110 7
b10 8
b11111111 6
1+
b1 1
b11 B
0&
b0 ?
1%
#570
0%
#575
b10110010 :
b10 9
b100 B
1&
b0 ?
0+
b0 1
1%
#580
0%
#585
b11111111 6
b1011011 7
b11 8
b11 0
1+
b1 1
b101 B
0&
b0 ?
1%
#590
0%
#595
b1011001 :
b11 9
b110 B
b0 ?
0+
b0 1
1%
#600
0%
#605
b100 0
b101101 7
1"
b100 8
b11111111 6
1+
b1 1
b111 B
1&
b0 ?
1%
#610
0%
#615
b1000101100 :
b100 9
b1000 B
b0 ?
0+
b0 1
1%
#620
0%
#625
b11111111 6
b10110 7
b101 8
b101 0
1+
b1 1
b1001 B
0&
b0 ?
1%
#630
0%
#635
b1100010110 :
b101 9
b1010 B
1&
b0 ?
0+
b0 1
1%
#640
0%
#645
b110 0
b1011 7
0"
b110 8
b11111111 6
1+
b1 1
0A
b0 B
1%
#650
0%
#655
b110001011 :
b110 9
0+
b0 1
1%
#660
0%
#665
b11111111 6
b101 7
1"
b111 8
b111 0
1+
b1 1
1%
#670
0%
#675
b1011000101 :
b111 9
0+
b0 1
1%
#680
0%
#685
b1000 0
b10 7
b1000 8
b11111111 6
1+
b1 1
1%
#690
0%
#695
b1101100010 :
b1000 9
0+
b0 1
1%
#700
0%
#705
b11111111 6
b1 7
0"
b1001 8
b1001 0
1+
b1 1
1%
#710
0%
#715
b110110001 :
b1001 9
0+
b0 1
1%
#720
0%
#725
b1010 0
b0 7
1"
b0 8
b11111111 6
1+
b1 1
1%
#730
0%
#735
1(
b1011011000 )
b1011011000 ;
b1011011000 >
b1011011000 :
b0 9
0+
b0 1
1%
#740
0%
#745
b11111111 6
0"
b101101100 7
b1 8
b11 4
b1 0
1+
b1 1
b1 B
0&
b1011011000 @
1A
b0 ?
1%
#750
0%
#755
0(
b101101100 :
b1 9
b10 B
b0 ?
0+
b0 1
1%
#760
0%
#765
b10 0
b10110110 7
b10 8
b11111111 6
1+
b1 1
b11 B
b0 ?
1%
#770
0%
#775
b10110110 :
b10 9
b100 B
1&
b0 ?
0+
b0 1
1%
#780
0%
#785
b11111111 6
b1011011 7
b11 8
b11 0
1+
b1 1
b101 B
b0 ?
1%
#790
0%
#795
b1011011 :
b11 9
b110 B
0&
b0 ?
0+
b0 1
1%
#800
0%
#805
b100 0
b101101 7
1"
b100 8
b11111111 6
1+
b1 1
b111 B
1&
b0 ?
1%
#810
0%
#815
b1000101101 :
b100 9
b1000 B
b0 ?
0+
b0 1
1%
#820
0%
#825
b11111111 6
b10110 7
b101 8
b101 0
1+
b1 1
b1001 B
0&
b0 ?
1%
#830
0%
#835
b1100010110 :
b101 9
b1010 B
1&
b0 ?
0+
b0 1
1%
#840
0%
#845
b110 0
b1011 7
0"
b110 8
b11111111 6
1+
b1 1
0A
b0 B
1%
#850
0%
#855
b110001011 :
b110 9
0+
b0 1
1%
#860
0%
#865
b11111111 6
b101 7
1"
b111 8
b111 0
1+
b1 1
1%
#870
0%
#875
b1011000101 :
b111 9
0+
b0 1
1%
#880
0%
#885
b1000 0
b10 7
b1000 8
b11111111 6
1+
b1 1
1%
#890
0%
#895
b1101100010 :
b1000 9
0+
b0 1
1%
#900
0%
#905
b11111111 6
b1 7
0"
b1001 8
b1001 0
1+
b1 1
1%
#910
0%
#915
b110110001 :
b1001 9
0+
b0 1
1%
#920
0%
#925
b1010 0
b0 7
1"
b0 8
b11111111 6
1+
b1 1
1%
#930
0%
#935
1(
b1011011000 :
b0 9
0+
b0 1
1%
#940
0%
#945
b11111111 6
0"
b101101111 7
b1 8
b1011011110 *
b1011011110 2
b1011011110 5
b100 4
b1 0
1+
b1 1
b1 B
0&
1A
b0 ?
1%
#950
0%
#955
0(
b101101100 :
b1 9
b10 B
b0 ?
0+
b0 1
1%
#960
0%
#965
b10 0
b10110111 7
1"
b10 8
b11111111 6
1+
b1 1
b11 B
b0 ?
1%
#970
0%
#975
b1010110110 :
b10 9
b100 B
1&
b0 ?
0+
b0 1
1%
#980
0%
#985
b11111111 6
b1011011 7
b11 8
b11 0
1+
b1 1
b101 B
b0 ?
1%
#990
0%
#995
b1101011011 :
b11 9
b110 B
0&
b0 ?
0+
b0 1
1%
#1000
0%
#1005
b100 0
b101101 7
b100 8
b11111111 6
1+
b1 1
b111 B
1&
b0 ?
1%
#1010
0%
#1015
b1110101101 :
b100 9
b1000 B
b0 ?
0+
b0 1
1%
#1020
0%
#1025
b11111111 6
b10110 7
b101 8
b101 0
1+
b1 1
b1001 B
0&
b0 ?
1%
#1030
0%
#1035
b1111010110 :
b101 9
b1010 B
1&
b0 ?
0+
b0 1
1%
#1040
0%
#1045
b110 0
b1011 7
0"
b110 8
b11111111 6
1+
b1 1
0A
b0 B
1%
#1050
0%
#1055
b111101011 :
b110 9
0+
b0 1
1%
#1060
0%
#1065
b11111111 6
b101 7
1"
b111 8
b111 0
1+
b1 1
1%
#1070
0%
#1075
b1011110101 :
b111 9
0+
b0 1
1%
#1080
0%
#1085
b1000 0
b10 7
b1000 8
b11111111 6
1+
b1 1
1%
#1090
0%
#1095
b1101111010 :
b1000 9
0+
b0 1
1%
#1100
0%
#1105
b11111111 6
b1 7
0"
b1001 8
b1001 0
1+
b1 1
1%
#1110
0%
#1115
b110111101 :
b1001 9
0+
b0 1
1%
#1120
0%
#1125
b1010 0
b0 7
1"
b0 8
b11111111 6
1+
b1 1
1%
#1130
0%
#1135
1(
b1011011110 )
b1011011110 ;
b1011011110 >
b1011011110 :
b0 9
0+
b0 1
1%
#1140
0%
#1145
b11111111 6
0"
b100101100 7
b1 8
b1001011000 *
b1001011000 2
b1001011000 5
b101 4
b1 0
1+
b1 1
b1 B
0&
b1011011110 @
1A
b0 ?
1%
#1150
0%
#1155
0(
b101101111 :
b1 9
b10 B
1&
b0 ?
0+
b0 1
1%
#1160
0%
#1165
b10 0
b10010110 7
b10 8
b11111111 6
1+
b1 1
b11 B
b0 ?
1%
#1170
0%
#1175
b10110111 :
b10 9
b100 B
b0 ?
0+
b0 1
1%
#1180
0%
#1185
b11111111 6
b1001011 7
b11 8
b11 0
1+
b1 1
b101 B
b0 ?
1%
#1190
0%
#1195
b1011011 :
b11 9
b110 B
0&
b0 ?
0+
b0 1
1%
#1200
0%
#1205
b100 0
b100101 7
1"
b100 8
b11111111 6
1+
b1 1
b111 B
1&
b0 ?
1%
#1210
0%
#1215
b1000101101 :
b100 9
b1000 B
b0 ?
0+
b0 1
1%
#1220
0%
#1225
b11111111 6
b10010 7
b101 8
b101 0
1+
b1 1
b1001 B
0&
b0 ?
1%
#1230
0%
#1235
b1100010110 :
b101 9
b1010 B
1&
b0 ?
0+
b0 1
1%
#1240
0%
#1245
b110 0
b1001 7
0"
b110 8
b11111111 6
1+
b1 1
0A
b0 B
1%
#1250
0%
#1255
b110001011 :
b110 9
0+
b0 1
1%
#1260
0%
#1265
b11111111 6
b100 7
1"
b111 8
b111 0
1+
b1 1
1%
#1270
0%
#1275
b1011000101 :
b111 9
0+
b0 1
1%
#1280
0%
#1285
b1000 0
b10 7
0"
b1000 8
b11111111 6
1+
b1 1
1%
#1290
0%
#1295
b101100010 :
b1000 9
0+
b0 1
1%
#1300
0%
#1305
b11111111 6
b1 7
b1001 8
b1001 0
1+
b1 1
1%
#1310
0%
#1315
b10110001 :
b1001 9
0+
b0 1
1%
#1320
0%
#1325
b1010 0
b0 7
1"
b0 8
b11111111 6
1+
b1 1
1%
#1330
0%
#1335
1(
b1001011000 )
b1001011000 ;
b1001011000 >
b1001011000 :
b0 9
0+
b0 1
1%
#1340
0%
#1345
b11111111 6
0"
b100100000 7
b1 8
b1001000000 *
b1001000000 2
b1001000000 5
b110 4
b1 0
1+
b1 1
b1 B
0&
b1001011000 @
1A
b0 ?
1%
#1350
0%
#1355
0(
b100101100 :
b1 9
b10 B
b0 ?
0+
b0 1
1%
#1360
0%
#1365
b10 0
b10010000 7
b10 8
b11111111 6
1+
b1 1
b11 B
b0 ?
1%
#1370
0%
#1375
b10010110 :
b10 9
b100 B
1&
b0 ?
0+
b0 1
1%
#1380
0%
#1385
b11111111 6
b1001000 7
b11 8
b11 0
1+
b1 1
b101 B
b0 ?
1%
#1390
0%
#1395
b1001011 :
b11 9
b110 B
0&
b0 ?
0+
b0 1
1%
#1400
0%
#1405
b100 0
b100100 7
b100 8
b11111111 6
1+
b1 1
b111 B
1&
b0 ?
1%
#1410
0%
#1415
b100101 :
b100 9
b1000 B
0&
b0 ?
0+
b0 1
1%
#1420
0%
#1425
b11111111 6
b10010 7
b101 8
b101 0
1+
b1 1
b1001 B
b0 ?
1%
#1430
0%
#1435
b10010 :
b101 9
b1010 B
1&
b0 ?
0+
b0 1
1%
#1440
0%
#1445
b110 0
b1001 7
b110 8
b11111111 6
1+
b1 1
0A
b0 B
1%
#1450
0%
#1455
b1001 :
b110 9
0+
b0 1
1%
#1460
0%
#1465
b11111111 6
b100 7
1"
b111 8
b111 0
1+
b1 1
1%
#1470
0%
#1475
b1000000100 :
b111 9
0+
b0 1
1%
#1480
0%
#1485
b1000 0
b10 7
0"
b1000 8
b11111111 6
1+
b1 1
1%
#1490
0%
#1495
b100000010 :
b1000 9
0+
b0 1
1%
#1500
0%
#1505
b11111111 6
b1 7
b1001 8
b1001 0
1+
b1 1
1%
#1510
0%
#1515
b10000001 :
b1001 9
0+
b0 1
1%
#1520
0%
#1525
b1010 0
b0 7
1"
b0 8
b11111111 6
1+
b1 1
1%
#1530
0%
#1535
1(
b1001000000 )
b1001000000 ;
b1001000000 >
b1001000000 :
b0 9
0+
b0 1
1%
#1540
0%
#1545
b11111111 6
0"
b101110110 7
b1 8
b1011101100 *
b1011101100 2
b1011101100 5
b111 4
b1 0
1+
b1 1
b1 B
0&
b1001000000 @
1A
b0 ?
1%
#1550
0%
#1555
0(
b100100000 :
b1 9
b10 B
b0 ?
0+
b0 1
1%
#1560
0%
#1565
b10 0
b10111011 7
b10 8
b11111111 6
1+
b1 1
b11 B
b0 ?
1%
#1570
0%
#1575
b10010000 :
b10 9
b100 B
b0 ?
0+
b0 1
1%
#1580
0%
#1585
b11111111 6
b1011101 7
1"
b11 8
b11 0
1+
b1 1
b101 B
b0 ?
1%
#1590
0%
#1595
b1001001000 :
b11 9
b110 B
b0 ?
0+
b0 1
1%
#1600
0%
#1605
b100 0
b101110 7
b100 8
b11111111 6
1+
b1 1
b111 B
1&
b0 ?
1%
#1610
0%
#1615
b1100100100 :
b100 9
b1000 B
0&
b0 ?
0+
b0 1
1%
#1620
0%
#1625
b11111111 6
b10111 7
0"
b101 8
b101 0
1+
b1 1
b1001 B
b0 ?
1%
#1630
0%
#1635
b110010010 :
b101 9
b1010 B
1&
b0 ?
0+
b0 1
1%
#1640
0%
#1645
b110 0
b1011 7
1"
b110 8
b11111111 6
1+
b1 1
0A
b0 B
1%
#1650
0%
#1655
b1011001001 :
b110 9
0+
b0 1
1%
#1660
0%
#1665
b11111111 6
b101 7
b111 8
b111 0
1+
b1 1
1%
#1670
0%
#1675
b1101100100 :
b111 9
0+
b0 1
1%
#1680
0%
#1685
b1000 0
b10 7
b1000 8
b11111111 6
1+
b1 1
1%
#1690
0%
#1695
b1110110010 :
b1000 9
0+
b0 1
1%
#1700
0%
#1705
b11111111 6
b1 7
0"
b1001 8
b1001 0
1+
b1 1
1%
#1710
0%
#1715
b111011001 :
b1001 9
0+
b0 1
1%
#1720
0%
#1725
b1010 0
b0 7
1"
b0 8
b11111111 6
1+
b1 1
1%
#1730
0%
#1735
1(
b1011101100 )
b1011101100 ;
b1011101100 >
b1011101100 :
b0 9
0+
b0 1
1%
#1740
0%
#1745
b11111111 6
0"
b101101100 7
b1 8
b1011011000 *
b1011011000 2
b1011011000 5
b1000 4
b1 0
1+
b1 1
b1 B
0&
b1011101100 @
1A
b0 ?
1%
#1750
0%
#1755
0(
b101110110 :
b1 9
b10 B
b0 ?
0+
b0 1
1%
#1760
0%
#1765
b10 0
b10110110 7
b10 8
b11111111 6
1+
b1 1
b11 B
1&
b0 ?
1%
#1770
0%
#1775
b10111011 :
b10 9
b100 B
b0 ?
0+
b0 1
1%
#1780
0%
#1785
b11111111 6
b1011011 7
b11 8
b11 0
1+
b1 1
b101 B
0&
b0 ?
1%
#1790
0%
#1795
b1011101 :
b11 9
b110 B
1&
b0 ?
0+
b0 1
1%
#1800
0%
#1805
b100 0
b101101 7
1"
b100 8
b11111111 6
1+
b1 1
b111 B
b0 ?
1%
#1810
0%
#1815
b1000101110 :
b100 9
b1000 B
b0 ?
0+
b0 1
1%
#1820
0%
#1825
b11111111 6
b10110 7
b101 8
b101 0
1+
b1 1
b1001 B
0&
b0 ?
1%
#1830
0%
#1835
b1100010111 :
b101 9
b1010 B
1&
b0 ?
0+
b0 1
1%
#1840
0%
#1845
b110 0
b1011 7
0"
b110 8
b11111111 6
1+
b1 1
0A
b0 B
1%
#1850
0%
#1855
b110001011 :
b110 9
0+
b0 1
1%
#1860
0%
#1865
b11111111 6
b101 7
1"
b111 8
b111 0
1+
b1 1
1%
#1870
0%
#1875
b1011000101 :
b111 9
0+
b0 1
1%
#1880
0%
#1885
b1000 0
b10 7
b1000 8
b11111111 6
1+
b1 1
1%
#1890
0%
#1895
b1101100010 :
b1000 9
0+
b0 1
1%
#1900
0%
#1905
b11111111 6
b1 7
0"
b1001 8
b1001 0
1+
b1 1
1%
#1910
0%
#1915
b110110001 :
b1001 9
0+
b0 1
1%
#1920
0%
#1925
b1010 0
b0 7
1"
b0 8
b11111111 6
1+
b1 1
1%
#1930
0%
#1935
1(
b1011011000 )
b1011011000 ;
b1011011000 >
b1011011000 :
b0 9
0+
b0 1
1%
#1940
0%
#1945
b11111111 6
0"
b101100001 7
b1 8
b1011000010 *
b1011000010 2
b1011000010 5
b1001 4
b1 0
1+
b1 1
b1 B
0&
b1011011000 @
1A
b0 ?
1%
#1950
0%
#1955
0(
b101101100 :
b1 9
b10 B
b0 ?
0+
b0 1
1%
#1960
0%
#1965
b10 0
b10110000 7
1"
b10 8
b11111111 6
1+
b1 1
b11 B
b0 ?
1%
#1970
0%
#1975
b1010110110 :
b10 9
b100 B
1&
b0 ?
0+
b0 1
1%
#1980
0%
#1985
b11111111 6
b1011000 7
0"
b11 8
b11 0
1+
b1 1
b101 B
b0 ?
1%
#1990
0%
#1995
b101011011 :
b11 9
b110 B
0&
b0 ?
0+
b0 1
1%
#2000
0%
#2005
b100 0
b101100 7
b100 8
b11111111 6
1+
b1 1
b111 B
1&
b0 ?
1%
#2010
0%
#2015
b10101101 :
b100 9
b1000 B
b0 ?
0+
b0 1
1%
#2020
0%
#2025
b11111111 6
b10110 7
b101 8
b101 0
1+
b1 1
b1001 B
0&
b0 ?
1%
#2030
0%
#2035
b1010110 :
b101 9
b1010 B
1&
b0 ?
0+
b0 1
1%
#2040
0%
#2045
b110 0
b1011 7
b110 8
b11111111 6
1+
b1 1
0A
b0 B
1%
#2050
0%
#2055
b101011 :
b110 9
0+
b0 1
1%
#2060
0%
#2065
b11111111 6
b101 7
1"
b111 8
b111 0
1+
b1 1
1%
#2070
0%
#2075
b1000010101 :
b111 9
0+
b0 1
1%
#2080
0%
#2085
b1000 0
b10 7
b1000 8
b11111111 6
1+
b1 1
1%
#2090
0%
#2095
b1100001010 :
b1000 9
0+
b0 1
1%
#2100
0%
#2105
b11111111 6
b1 7
0"
b1001 8
b1001 0
1+
b1 1
1%
#2110
0%
#2115
b110000101 :
b1001 9
0+
b0 1
1%
#2120
0%
#2125
b1010 0
b0 7
1"
b0 8
b11111111 6
1+
b1 1
1%
#2130
0%
#2135
1(
b1011000010 )
b1011000010 ;
b1011000010 >
b1011000010 :
b0 9
0+
b0 1
1%
#2140
0%
#2145
b11111111 6
0"
b101100100 7
b1 8
b1011001000 *
b1011001000 2
b1011001000 5
b1010 4
b1 0
1+
b1 1
b1 B
0&
b1011000010 @
1A
b0 ?
1%
#2150
0%
#2155
0(
b101100001 :
b1 9
b10 B
1&
b0 ?
0+
b0 1
1%
#2160
0%
#2165
b10 0
b10110010 7
b10 8
b11111111 6
1+
b1 1
b11 B
0&
b0 ?
1%
#2170
0%
#2175
b10110000 :
b10 9
b100 B
b0 ?
0+
b0 1
1%
#2180
0%
#2185
b11111111 6
b1011001 7
b11 8
b11 0
1+
b1 1
b101 B
b0 ?
1%
#2190
0%
#2195
b1011000 :
b11 9
b110 B
b0 ?
0+
b0 1
1%
#2200
0%
#2205
b100 0
b101100 7
1"
b100 8
b11111111 6
1+
b1 1
b111 B
1&
b0 ?
1%
#2210
0%
