lab4/src/led.v
module led #(parameter package_size = 8)
(
    input clk,
    input [package_size-1:0]data,
    input data_ready,
    output led
);
    reg led_ready = 0;
    reg [23:0] counter = 0;
    reg [package_size-1:0] flash_counter = 0;

    assign led = ((counter <= 6_750_000) && ((led_ready) || data_ready));


    always @(posedge clk) begin
        if (data_ready || led_ready) begin
            led_ready = 1;
            if (counter == 13_500_000) begin
                counter = 0;
                flash_counter = flash_counter + 1; 
            end
            else begin
                counter = counter + 1;
            end
            if (flash_counter == data) begin
                flash_counter = 0;
                led_ready = 0;
            end
        end
    end
endmodule

lab4/src/uart_rx.v
module uart_rx#(parameter transfer_speed = 4800, parameter package_size = 8, 
                parameter frequency = 27_000_000)
(
    input clk,
    input recieved_signal,
    output reg data_ready,
    output reg [package_size-1:0] data
);
    
    integer i = package_size - 1;
    parameter count_of_strobe = frequency / transfer_speed;
    parameter PAUSE = 0; parameter START = 1; 
    parameter READ = 2; parameter PARITY_CHECK = 3; 
    parameter STOP = 4;

    reg prev_recieved_signal;
    reg [2:0] state = 0;
    reg [25:0] count = 0;
    reg [package_size-1:0] count_ones = 0;

    always @(posedge clk) begin
        case(state)
            PAUSE: begin
                data_ready = 0;
                if (recieved_signal == 0)
                    count = count + 1;
                else
                    count = 0;
                if (count == count_of_strobe / 2)
                    state = state + 1;
            end

            START: begin
                if (recieved_signal == 0) begin
                    count = count + 1;
                end
                else begin
                    state = PAUSE;
                    count = 0;
                end
                if (count == count_of_strobe) begin
                    count = 0;
                    state = state + 1;
                end
            end

            READ: begin
                count = count + 1;
                if (count == 1) begin
                    prev_recieved_signal = recieved_signal;
                end
                if (prev_recieved_signal != recieved_signal) begin
                    state = PAUSE;
                    count = 0;
                end
                else begin
                    data[i] = recieved_signal;
                    if (count == count_of_strobe) begin
                        count = 0;
                        i = i - 1;
                    end
                    if (i == -1) begin
                        state = state + 1;
                        i = package_size - 1;
                    end
                    prev_recieved_signal = recieved_signal;
                end
            end

            PARITY_CHECK: begin
                count = count + 1;
                if (count == 1) begin
                    prev_recieved_signal = recieved_signal;
                end
                if (prev_recieved_signal != recieved_signal) begin
                    state = PAUSE;
                    count = 0;
                end
                else begin
                    if (count == count_of_strobe) begin
                        count = 0;
                        i = 0;
                        for (i = 0; i < package_size; i = i + 1)
                            count_ones = count_ones + data[i];
                        if ((count_ones + recieved_signal) % 2 == 0) begin
                            state = state + 1;
                        end
                        else begin
                            state = PAUSE;
                            count = 0;
                        end
                        count_ones = 0;
                        i = package_size - 1;
                    end
                end
            end

            STOP: begin
                if (recieved_signal == 1) begin
                    count = count + 1;
                end
                else begin
                    state = PAUSE;
                    count = 0;
                end
                if (count == count_of_strobe) begin
                    count = 0;
                    state = PAUSE;
                    data_ready = 1;
                end
            end
        endcase
    end
endmodule

lab4/src/uart_tx.v
module uart_tx#(parameter transfer_speed = 4800, parameter package_size = 8, 
                parameter frequency = 27_000_000)
(
    input clk,
    input [package_size+2:0] data,
    input data_update,
    output reg transmitted_signal
);


    parameter count_of_strobe = frequency / transfer_speed;
    reg [26:0] count = 0;
    integer i = package_size + 2;
    reg sending_data = 0;
    reg [package_size-1:0] flash_counter = 0;
    reg [package_size+2:0] recieved_data = 0;

    always @(posedge clk) begin
        if (data_update || sending_data) begin
            if (i == -1) begin
                count = 0;
                i = package_size + 2;
                sending_data = 0;
            end
            else begin
                if (!sending_data) begin
                    sending_data = 1;
                    recieved_data = data;
                end
                count = count + 1;
                transmitted_signal = recieved_data[i];
                if (count == count_of_strobe) begin
                    count = 0;
                    i = i - 1;
                end
            end
            
        end
        else begin
            transmitted_signal = 1;
        end
    end    
endmodule

lab4/src/data_reader.v
module data_reader#(parameter package_size = 8, parameter frequency = 27_000_000)
(
    input clk,
    input button1,
    input button2,
    output reg [package_size+2:0] data,
    output reg data_update
);


    parameter debouncer_limit = frequency / 100;
    integer i = 0;
    reg prev_button1 = 1;
    reg prev_button2 = 1;
    reg button1_pressed = 0;
    reg button2_pressed = 0;
    reg button1_stable = 0;
    reg button2_stable = 0;
    reg [18:0] button1_counter = 0;
    reg [18:0] button2_counter = 0;
    reg [package_size-1:0] number_of_press = 0;
    reg [package_size-1:0] press_counter = 0;
    reg [package_size-1:0] count_ones = 0;
    reg even_bit;
 

    always @(posedge clk) begin
        /*Начало устранение дребезга контактов на button1.*/
        if (!button1 && prev_button1) begin
            button1_pressed = 1;
        end
        else if (button1_pressed)
            button1_counter = button1_counter + 1;
        if (button1_counter == debouncer_limit)
            button1_stable = 1;
        /*Конец устранение дребезга контактов на button1.*/

        /*Кнопка button1 "явно" нажата.*/
        if (button1_stable && !button1) begin
            number_of_press = number_of_press + 1;
            button1_stable = 0;
            button1_pressed = 0;
            button1_counter = 0;
        end
        prev_button1 = button1;


        /*Начало устранение дребезга контактов на button2.*/
        if (!button2 && prev_button2) begin
            button2_pressed = 1;
        end
        else if (button2_pressed)
            button2_counter = button2_counter + 1;
        if (button2_counter == debouncer_limit)
            button2_stable = 1;
        /*Конец устранение дребезга контактов на button2.*/

        /*Кнопка button2 "явно" нажата.*/
        if (button2_stable && !button2) begin
            i = 0;
            for (i = 0; i < package_size; i = i + 1)
                count_ones = count_ones + number_of_press[i];
            even_bit = count_ones % 2;
            data = {1'b0, number_of_press, even_bit, 1'b1};
            data_update = 1;
            button2_stable = 0;
            button2_pressed = 0;
            button2_counter = 0;
            number_of_press = 0;
            count_ones = 0;
        end
        else begin
            data_update = 0;
        end
        prev_button2 = button2;
    end
endmodule

lab4/src/top.v
module top (
    input clk,
    input button1,
    input button2,
    output led
);
    wire [10:0] data_input;
    wire [7:0] data_output;
    data_reader #(8, 27_000_000) data_reader_inst (.clk(clk), .button1(button1), .button2(button2), .data(data_input), .data_update(data_update));
    uart_tx #(4800, 8, 27_000_000) uart_tx_inst(.clk(clk), .data(data_input), .data_update(data_update), .transmitted_signal(transmitted_signal));
    uart_rx #(4800, 8, 27_000_000) uart_rx_inst(.clk(clk), .recieved_signal(transmitted_signal), .data_ready(data_ready), .data(data_output));
    led #(8) led_inst(.clk(clk), .data(data_output), .data_ready(data_ready), .led(led));
endmodule

lab4/src/testbench.v
`timescale 1 ms / 1 ms

module testbench();
    reg clk = 0;
    reg button1 = 1;
    reg button2 = 1;
    wire led;
    top top_inst(
        .clk(clk),
        .button1(button1),
        .button2(button2),
        .led(led)
    );

    always #5 clk = ~clk;
    initial begin
        $dumpvars;
        $display("Test started...");
        #100 button1 = ~button1;
        #100 button1 = ~button1;
        #200 button2 = ~button2;
        #200 button2 = ~button2;
        /*
        #1000 button1 = ~button1;
        #30 button1 = ~button1;
        #30 button1 = ~button1;
        #30 button1 = ~button1;
        #30 button2 = ~button2;
        #30 button2 = ~button2;
        */
        #10000 $finish;
    end

endmodule

lab4/src/dump.vcd
$date
	Tue Nov 28 01:13:28 2023
$end
$version
	Icarus Verilog
$end
$timescale
	1ms
$end
$scope module testbench $end
$var wire 1 ! led $end
$var reg 1 " button1 $end
$var reg 1 # button2 $end
$var reg 1 $ clk $end
$scope module top_inst $end
$var wire 1 " button1 $end
$var wire 1 # button2 $end
$var wire 1 $ clk $end
$var wire 1 % transmitted_signal $end
$var wire 1 ! led $end
$var wire 1 & data_update $end
$var wire 1 ' data_ready $end
$var wire 8 ( data_output [7:0] $end
$var wire 11 ) data_input [10:0] $end
$scope module data_reader_inst $end
$var wire 1 " button1 $end
$var wire 1 # button2 $end
$var wire 1 $ clk $end
$var reg 19 * button1_counter [18:0] $end
$var reg 1 + button1_pressed $end
$var reg 1 , button1_stable $end
$var reg 19 - button2_counter [18:0] $end
$var reg 1 . button2_pressed $end
$var reg 1 / button2_stable $end
$var reg 8 0 count_ones [7:0] $end
$var reg 11 1 data [10:0] $end
$var reg 1 & data_update $end
$var reg 1 2 even_bit $end
$var reg 8 3 number_of_press [7:0] $end
$var reg 8 4 press_counter [7:0] $end
$var reg 1 5 prev_button1 $end
$var reg 1 6 prev_button2 $end
$var integer 32 7 i [31:0] $end
$upscope $end
$scope module led_inst $end
$var wire 1 $ clk $end
$var wire 1 ! led $end
$var wire 1 ' data_ready $end
$var wire 8 8 data [7:0] $end
$var reg 24 9 counter [23:0] $end
$var reg 8 : flash_counter [7:0] $end
$var reg 1 ; led_ready $end
$upscope $end
$scope module uart_rx_inst $end
$var wire 1 $ clk $end
$var wire 1 % recieved_signal $end
$var reg 26 < count [25:0] $end
$var reg 8 = count_ones [7:0] $end
$var reg 8 > data [7:0] $end
$var reg 1 ' data_ready $end
$var reg 1 ? prev_recieved_signal $end
$var reg 3 @ state [2:0] $end
$var integer 32 A i [31:0] $end
$upscope $end
$scope module uart_tx_inst $end
$var wire 1 $ clk $end
$var wire 11 B data [10:0] $end
$var wire 1 & data_update $end
$var reg 27 C count [26:0] $end
$var reg 8 D flash_counter [7:0] $end
$var reg 11 E recieved_data [10:0] $end
$var reg 1 F sending_data $end
$var reg 1 % transmitted_signal $end
$var integer 32 G i [31:0] $end
$upscope $end
$upscope $end
$upscope $end
$enddefinitions $end
#0
$dumpvars
b1010 G
0F
b0 E
b0 D
b0 C
bx B
b111 A
b0 @
x?
bx >
b0 =
b0 <
0;
b0 :
b0 9
bx 8
b0 7
16
15
b0 4
b0 3
x2
bx 1
b0 0
0/
0.
b0 -
0,
0+
b0 *
bx )
bx (
x'
x&
x%
0$
1#
1"
0!
$end
#5
0&
1%
0'
1$
#10
0$
#15
1$
#20
0$
#25
1$
#30
0$
#35
1$
#40
0$
#45
1$
#50
0$
#55
1$
#60
0$
#65
1$
#70
0$
#75
1$
#80
0$
#85
1$
#90
0$
#95
1$
#100
0$
0"
#105
05
1+
1$
#110
0$
#115
0+
b1 3
0,
b0 *
1$
#120
0$
#125
1$
#130
0$
#135
1$
#140
0$
#145
1$
#150
0$
#155
1$
#160
0$
#165
1$
#170
0$
#175
1$
#180
0$
#185
1$
#190
0$
#195
1$
#200
0$
1"
#205
15
1$
#210
0$
#215
1$
#220
0$
#225
1$
#230
0$
#235
1$
#240
0$
#245
1$
#250
0$
#255
1$
#260
0$
#265
1$
#270
0$
#275
1$
#280
0$
#285
1$
#290
0$
#295
1$
#300
0$
#305
1$
#310
0$
#315
1$
#320
0$
#325
1$
#330
0$
#335
1$
#340
0$
#345
1$
#350
0$
#355
1$
#360
0$
#365
1$
#370
0$
#375
1$
#380
0$
#385
1$
#390
0$
#395
1$
#400
0$
0#
#405
06
1.
1$
#410
0$
#415
b1 <
0%
b1 C
b111 E
1F
b0 3
0.
1&
b111 )
b111 1
b111 B
12
b1000 7
b0 0
0/
b0 -
1$
#420
0$
#425
0&
b10 C
b1 @
b10 <
1$
#430
0$
#435
b11 <
b11 C
1$
#440
0$
#445
b1001 G
b0 C
b10 @
b0 <
1$
#450
0$
#455
b0xxxxxxx (
b0xxxxxxx 8
b0xxxxxxx >
0?
b1 <
b1 C
1$
#460
0$
#465
b10 C
b10 <
1$
#470
0$
#475
b11 <
b11 C
1$
#480
0$
#485
b1000 G
b0 C
b110 A
b0 <
1$
#490
0$
#495
b0xxxxxx (
b0xxxxxx 8
b0xxxxxx >
b1 <
b1 C
1$
#500
0$
#505
b10 C
b10 <
1$
#510
0$
#515
b11 <
b11 C
1$
#520
0$
#525
b111 G
b0 C
b101 A
b0 <
1$
#530
0$
#535
b0xxxxx (
b0xxxxx 8
b0xxxxx >
b1 <
b1 C
1$
#540
0$
#545
b10 C
b10 <
1$
#550
0$
#555
b11 <
b11 C
1$
#560
0$
#565
b110 G
b0 C
b100 A
b0 <
1$
#570
0$
#575
b0xxxx (
b0xxxx 8
b0xxxx >
b1 <
b1 C
1$
#580
0$
#585
b10 C
b10 <
1$
#590
0$
#595
b11 <
b11 C
1$
#600
0$
1#
#605
16
b101 G
b0 C
b11 A
b0 <
1$
#610
0$
#615
b0xxx (
b0xxx 8
b0xxx >
b1 <
b1 C
1$
#620
0$
#625
b10 C
b10 <
1$
#630
0$
#635
b11 <
b11 C
1$
#640
0$
#645
b100 G
b0 C
b10 A
b0 <
1$
#650
0$
#655
b0xx (
b0xx 8
b0xx >
b1 <
b1 C
1$
#660
0$
#665
b10 C
b10 <
1$
#670
0$
#675
b11 <
b11 C
1$
#680
0$
#685
b11 G
b0 C
b1 A
b0 <
1$
#690
0$
#695
b0x (
b0x 8
b0x >
b1 <
b1 C
1$
#700
0$
#705
b10 C
b10 <
1$
#710
0$
#715
b11 <
b11 C
1$
#720
0$
#725
b10 G
b0 C
b0 A
b0 <
1$
#730
0$
#735
b1 (
b1 8
b1 >
1?
b1 <
1%
b1 C
1$
#740
0$
#745
b10 C
b10 <
1$
#750
0$
#755
b11 <
b11 C
1$
#760
0$
#765
b1 G
b0 C
b11 @
b111 A
b0 <
1$
#770
0$
#775
b1 <
b1 C
1$
#780
0$
#785
b10 C
b10 <
1$
#790
0$
#795
b11 <
b11 C
1$
#800
0$
#805
b0 G
b0 C
b100 @
b0 =
b1000 A
b0 <
1$
#810
0$
#815
b1 <
b1 C
1$
#820
0$
#825
b10 C
b10 <
1$
#830
0$
#835
b11 <
b11 C
1$
#840
0$
#845
b11111111111111111111111111111111 G
b0 C
1'
b0 @
b0 <
1$
#850
0$
#855
0'
0F
b1010 G
1$
